[
    {
		"name": "Forest",
		"type": "TerrainFeature",
		"production": 1,
		"food": 1,
		"movementCost": 2,
		"overrideStats": true,
		"unbuildable": true,
		"defenceBonus": 0.25,
		"occursOn": ["Tundra","Plains","Grassland","Hill"],
		"uniques": ["Rough terrain", "Vegetation",
					"Provides a one-time bonus of [+30 Production] to the closest city when cut down <(modified by game speed)>",
                    "Provides a one-time bonus of [+90 Production] to the closest city when cut down <(modified by game speed)><for [Tanino Gimlet] Civilizations>",
					"Blocks line-of-sight from tiles at same elevation",
					"[25]% Chance to be destroyed by nukes",
					"A Region is formed with at least [30]% [Forest] tiles, with priority [3]",
					"A Region is formed with at least [35]% [Forest] tiles and [Jungle] tiles, with priority [3]",
					"A Region can not contain more [Jungle] tiles than [Forest] tiles",
					"Considered [Desirable] when determining start locations",
					"Considered [Production] when determining start locations",
					"Considered [Food] when determining start locations <in [Forest] Regions>",
					"Considered [Food] when determining start locations <in [Tundra] Regions>",
					"Every [39] tiles with this terrain will receive a major deposit of a strategic resource."],
		"civilopediaText": [{"text":"A Camp can be built here without cutting it down", "link":"Improvement/Camp"}]
	},
]